alibabacloud_paistudio20220112/__init__.py
alibabacloud_paistudio20220112/client.py
alibabacloud_paistudio20220112/models/__init__.py
alibabacloud_paistudio20220112/models/_acs.py
alibabacloud_paistudio20220112/models/_action.py
alibabacloud_paistudio20220112/models/_algorithm_spec.py
alibabacloud_paistudio20220112/models/_allocate_strategy_spec.py
alibabacloud_paistudio20220112/models/_assign_node_spec.py
alibabacloud_paistudio20220112/models/_binding_policy.py
alibabacloud_paistudio20220112/models/_cache_info.py
alibabacloud_paistudio20220112/models/_cache_service.py
alibabacloud_paistudio20220112/models/_capacity_lock.py
alibabacloud_paistudio20220112/models/_channel.py
alibabacloud_paistudio20220112/models/_channel_property.py
alibabacloud_paistudio20220112/models/_check_instance_web_terminal_request.py
alibabacloud_paistudio20220112/models/_check_instance_web_terminal_response.py
alibabacloud_paistudio20220112/models/_check_instance_web_terminal_response_body.py
alibabacloud_paistudio20220112/models/_cluster_spec.py
alibabacloud_paistudio20220112/models/_component_spec.py
alibabacloud_paistudio20220112/models/_condition_expression.py
alibabacloud_paistudio20220112/models/_create_algorithm_request.py
alibabacloud_paistudio20220112/models/_create_algorithm_response.py
alibabacloud_paistudio20220112/models/_create_algorithm_response_body.py
alibabacloud_paistudio20220112/models/_create_algorithm_version_request.py
alibabacloud_paistudio20220112/models/_create_algorithm_version_response.py
alibabacloud_paistudio20220112/models/_create_algorithm_version_response_body.py
alibabacloud_paistudio20220112/models/_create_algorithm_version_shrink_request.py
alibabacloud_paistudio20220112/models/_create_instance_web_terminal_response.py
alibabacloud_paistudio20220112/models/_create_instance_web_terminal_response_body.py
alibabacloud_paistudio20220112/models/_create_quota_request.py
alibabacloud_paistudio20220112/models/_create_quota_response.py
alibabacloud_paistudio20220112-2.2.4.dist-info/LICENSE
alibabacloud_paistudio20220112-2.2.4.dist-info/METADATA
alibabacloud_paistudio20220112-2.2.4.dist-info/WHEEL
alibabacloud_paistudio20220112-2.2.4.dist-info/top_level.txt
alibabacloud_paistudio20220112-2.2.4.dist-info/RECORD
